scrapyd_client/__init__.py
scrapyd_client/__main__.py
scrapyd_client/deploy.py
scrapyd_client/exceptions.py
scrapyd_client/pyclient.py
scrapyd_client/utils.py
scrapyd_client-2.0.3.dist-info/LICENSE
scrapyd_client-2.0.3.dist-info/METADATA
scrapyd_client-2.0.3.dist-info/WHEEL
scrapyd_client-2.0.3.dist-info/entry_points.txt
scrapyd_client-2.0.3.dist-info/top_level.txt
scrapyd_client-2.0.3.dist-info/RECORD
