Metadata-Version: 2.1
Name: scrapyd-client
Version: 2.0.3
Summary: A client for Scrapyd
Author-email: Scrapy developers <info@scrapy.org>
License: BSD
Project-URL: Homepage, https://github.com/scrapy/scrapyd-client
Classifier: Framework :: Scrapy
Classifier: Development Status :: 5 - Production/Stable
Classifier: Environment :: Console
Classifier: Intended Audience :: Developers
Classifier: Topic :: Internet :: WWW/HTTP
Classifier: License :: OSI Approved :: BSD License
Classifier: Operating System :: OS Independent
Classifier: Programming Language :: Python :: 3.9
Classifier: Programming Language :: Python :: 3.10
Classifier: Programming Language :: Python :: 3.11
Classifier: Programming Language :: Python :: 3.12
Classifier: Programming Language :: Python :: 3.13
Classifier: Programming Language :: Python :: Implementation :: CPython
Classifier: Programming Language :: Python :: Implementation :: PyPy
License-File: LICENSE
Requires-Dist: pip
Requires-Dist: requests
Requires-Dist: scrapy>=0.17
Requires-Dist: setuptools
Requires-Dist: uberegg>=0.1.1
Provides-Extra: test
Requires-Dist: coverage; extra == "test"
Requires-Dist: pytest; extra == "test"
Requires-Dist: pytest-console-scripts; extra == "test"
Requires-Dist: pytest-mock; extra == "test"
